odoo/addons/partner_category_security/README.rst
odoo/addons/partner_category_security/__init__.py
odoo/addons/partner_category_security/__manifest__.py
odoo/addons/partner_category_security/i18n/es.po
odoo/addons/partner_category_security/i18n/it.po
odoo/addons/partner_category_security/i18n/partner_category_security.pot
odoo/addons/partner_category_security/models/__init__.py
odoo/addons/partner_category_security/models/ir_ui_menu.py
odoo/addons/partner_category_security/models/res_partner.py
odoo/addons/partner_category_security/readme/CONTRIBUTORS.md
odoo/addons/partner_category_security/readme/DESCRIPTION.md
odoo/addons/partner_category_security/readme/USAGE.md
odoo/addons/partner_category_security/security/ir.model.access.csv
odoo/addons/partner_category_security/security/security.xml
odoo/addons/partner_category_security/static/description/icon.png
odoo/addons/partner_category_security/static/description/index.html
odoo/addons/partner_category_security/tests/__init__.py
odoo/addons/partner_category_security/tests/test_partner_category_security.py
odoo/addons/partner_category_security/views/menu.xml
odoo_addon_partner_category_security-17.0.1.0.0.3.dist-info/METADATA
odoo_addon_partner_category_security-17.0.1.0.0.3.dist-info/WHEEL
odoo_addon_partner_category_security-17.0.1.0.0.3.dist-info/top_level.txt
odoo_addon_partner_category_security-17.0.1.0.0.3.dist-info/RECORD
